aiologic/__init__.py
aiologic/_barrier.py
aiologic/_barrier.pyi
aiologic/_condition.py
aiologic/_condition.pyi
aiologic/_decorator.py
aiologic/_decorator.pyi
aiologic/_event.py
aiologic/_event.pyi
aiologic/_flag.py
aiologic/_flag.pyi
aiologic/_guard.py
aiologic/_guard.pyi
aiologic/_limiter.py
aiologic/_limiter.pyi
aiologic/_lock.py
aiologic/_lock.pyi
aiologic/_queue.py
aiologic/_queue.pyi
aiologic/_semaphore.py
aiologic/_semaphore.pyi
aiologic/py.typed
aiologic/_monkey/__init__.py
aiologic/_monkey/_originals.py
aiologic/_monkey/_originals.pyi
aiologic/_monkey/_patcher.py
aiologic/_monkey/_patcher.pyi
aiologic/_testing/__init__.py
aiologic/_testing/_checkpoints.py
aiologic/_testing/_checkpoints.pyi
aiologic/_testing/_constants.py
aiologic/_testing/_constants.pyi
aiologic/_testing/_exceptions.py
aiologic/_testing/_exceptions.pyi
aiologic/_testing/_executors.py
aiologic/_testing/_executors.pyi
aiologic/_testing/_groups.py
aiologic/_testing/_groups.pyi
aiologic/_testing/_results.py
aiologic/_testing/_results.pyi
aiologic/_testing/_runners.py
aiologic/_testing/_runners.pyi
aiologic/_testing/_tasks.py
aiologic/_testing/_tasks.pyi
aiologic/_testing/_timeouts.py
aiologic/_testing/_timeouts.pyi
aiologic/lowlevel/__init__.py
aiologic/lowlevel/_checkpoints.py
aiologic/lowlevel/_checkpoints.pyi
aiologic/lowlevel/_events.py
aiologic/lowlevel/_events.pyi
aiologic/lowlevel/_greenlets.py
aiologic/lowlevel/_greenlets.pyi
aiologic/lowlevel/_ident.py
aiologic/lowlevel/_ident.pyi
aiologic/lowlevel/_libraries.py
aiologic/lowlevel/_libraries.pyi
aiologic/lowlevel/_locks.py
aiologic/lowlevel/_locks.pyi
aiologic/lowlevel/_queues.py
aiologic/lowlevel/_queues.pyi
aiologic/lowlevel/_safety.py
aiologic/lowlevel/_safety.pyi
aiologic/lowlevel/_tasks.py
aiologic/lowlevel/_tasks.pyi
aiologic/lowlevel/_threads.py
aiologic/lowlevel/_threads.pyi
aiologic/lowlevel/_time.py
aiologic/lowlevel/_time.pyi
aiologic/lowlevel/_waiters.py
aiologic/lowlevel/_waiters.pyi
aiologic/meta/__init__.py
aiologic-0.15.0.dist-info/METADATA
aiologic-0.15.0.dist-info/WHEEL
aiologic-0.15.0.dist-info/RECORD
