Metadata-Version: 2.4
Name: aiologic
Version: 0.15.0
Summary: GIL-powered* locking library for Python
Project-URL: Homepage, https://github.com/x42005e1f/aiologic
Project-URL: Documentation, https://aiologic.readthedocs.io
Project-URL: Changelog, https://aiologic.readthedocs.io/latest/changelog.html
Author-email: Ilya Egorov <0x42005e1f@gmail.com>
Keywords: anyio,async,async-await,asyncio,concurrency,eventlet,gevent,greenlet,library,locking,mypy,python,synchronization,thread-safety,threading,trio
Classifier: Development Status :: 3 - Alpha
Classifier: Framework :: AnyIO
Classifier: Framework :: AsyncIO
Classifier: Framework :: Trio
Classifier: Intended Audience :: Developers
Classifier: License :: OSI Approved :: ISC License (ISCL)
Classifier: Operating System :: OS Independent
Classifier: Programming Language :: Python :: 3 :: Only
Classifier: Programming Language :: Python :: 3.8
Classifier: Programming Language :: Python :: 3.9
Classifier: Programming Language :: Python :: 3.10
Classifier: Programming Language :: Python :: 3.11
Classifier: Programming Language :: Python :: 3.12
Classifier: Programming Language :: Python :: 3.13
Classifier: Programming Language :: Python :: 3.14
Classifier: Programming Language :: Python :: Free Threading :: 2 - Beta
Classifier: Programming Language :: Python :: Implementation :: CPython
Classifier: Programming Language :: Python :: Implementation :: PyPy
Classifier: Topic :: Software Development :: Libraries :: Python Modules
Classifier: Typing :: Typed
Requires-Python: >=3.8
Requires-Dist: sniffio>=1.3.0
Requires-Dist: typing-extensions>=4.5.0; python_version < '3.13'
Requires-Dist: wrapt>=1.16.0
Provides-Extra: anyio
Requires-Dist: anyio>=3.0.0; extra == 'anyio'
Provides-Extra: curio
Requires-Dist: curio>=1.4; extra == 'curio'
Provides-Extra: eventlet
Requires-Dist: eventlet>=0.17.0; extra == 'eventlet'
Provides-Extra: gevent
Requires-Dist: gevent>=21.1.0; extra == 'gevent'
Provides-Extra: trio
Requires-Dist: trio>=0.23.0; extra == 'trio'
Provides-Extra: trio-asyncio
Requires-Dist: trio-asyncio>=0.13.0; extra == 'trio-asyncio'
